mdtpy/__init__.py
mdtpy/cli.py
mdtpy/types.py
mdtpy/client/__init__.py
mdtpy/client/http_client.py
mdtpy/client/http_fa3st_client.py
mdtpy/client/http_instance_client.py
mdtpy/client/http_registry_client.py
mdtpy/client/http_repository_client.py
mdtpy/client/http_service_client.py
mdtpy/client/utils.py
mdtpy/impl/__init__.py
mdtpy/impl/json_deserializer.py
mdtpy/model/__init__.py
mdtpy/model/aas_model.py
mdtpy/model/aas_registry.py
mdtpy/model/aas_repository.py
mdtpy/model/aas_service.py
mdtpy/model/datatype_def_xsd.py
mdtpy/model/exceptions.py
mdtpy/model/ksx9101.py
mdtpy/model/mdt.py
mdtpy/model/reference.py
mdtpy/model/timeseries.py
mdtpy/model/value.py
mdtpy-25.11.10.dist-info/METADATA
mdtpy-25.11.10.dist-info/WHEEL
mdtpy-25.11.10.dist-info/top_level.txt
mdtpy-25.11.10.dist-info/RECORD
