Metadata-Version: 2.1
Name: mdtpy
Version: 25.11.10
Summary: MDT client for Python
Home-page: https://github.com/kwlee0220/mdtpy
Author: Kang-Woo Lee
Author-email: kwlee@etri.re.kr
License: UNKNOWN
Platform: UNKNOWN
Requires-Python: >=3.10
Requires-Dist: dataclasses-json
Requires-Dist: requests
Requires-Dist: requests-toolbelt
